pypaperless/__init__.py
pypaperless/api.py
pypaperless/const.py
pypaperless/exceptions.py
pypaperless/helpers.py
pypaperless/py.typed
pypaperless/models/__init__.py
pypaperless/models/base.py
pypaperless/models/classifiers.py
pypaperless/models/common.py
pypaperless/models/config.py
pypaperless/models/custom_fields.py
pypaperless/models/documents.py
pypaperless/models/mails.py
pypaperless/models/pages.py
pypaperless/models/permissions.py
pypaperless/models/remote_version.py
pypaperless/models/saved_views.py
pypaperless/models/share_links.py
pypaperless/models/statistics.py
pypaperless/models/status.py
pypaperless/models/tasks.py
pypaperless/models/workflows.py
pypaperless/models/generators/__init__.py
pypaperless/models/generators/page.py
pypaperless/models/mixins/__init__.py
pypaperless/models/mixins/helpers/__init__.py
pypaperless/models/mixins/helpers/callable.py
pypaperless/models/mixins/helpers/draftable.py
pypaperless/models/mixins/helpers/iterable.py
pypaperless/models/mixins/helpers/securable.py
pypaperless/models/mixins/models/__init__.py
pypaperless/models/mixins/models/creatable.py
pypaperless/models/mixins/models/data_fields.py
pypaperless/models/mixins/models/deletable.py
pypaperless/models/mixins/models/securable.py
pypaperless/models/mixins/models/updatable.py
pypaperless/models/utils/__init__.py
pypaperless-5.2.2.dist-info/METADATA
pypaperless-5.2.2.dist-info/WHEEL
pypaperless-5.2.2.dist-info/licenses/LICENSE.md
pypaperless-5.2.2.dist-info/RECORD
