Metadata-Version: 2.4
Name: pypaperless
Version: 5.2.2
Summary: Little api client for paperless(-ngx).
Project-URL: Homepage, https://github.com/tb1337/paperless-api
Project-URL: Source Code, https://github.com/tb1337/paperless-api
Project-URL: Bug Reports, https://github.com/tb1337/paperless-api/issues
Project-URL: Coverage, https://codecov.io/gh/tb1337/paperless-api
Author-email: Tobias Schulz <public.dev@tbsch.de>
License: MIT
License-File: LICENSE.md
Keywords: api-client,async,library,paperless-ngx,python3
Classifier: Development Status :: 5 - Production/Stable
Classifier: Framework :: AsyncIO
Classifier: Intended Audience :: Developers
Classifier: License :: OSI Approved :: MIT License
Classifier: Programming Language :: Python :: 3.12
Classifier: Programming Language :: Python :: 3.13
Classifier: Programming Language :: Python :: 3.14
Classifier: Topic :: Software Development :: Libraries :: Python Modules
Requires-Python: <3.15,>=3.12
Requires-Dist: aiohttp>=3.13.2
Requires-Dist: yarl>=1.22.0
